libertem_blobfinder/__init__.py
libertem_blobfinder/__version__.py
libertem_blobfinder/versioning.py
libertem_blobfinder/base/__init__.py
libertem_blobfinder/base/correlation.py
libertem_blobfinder/base/masks.py
libertem_blobfinder/base/utils.py
libertem_blobfinder/common/__init__.py
libertem_blobfinder/common/correlation.py
libertem_blobfinder/common/fullmatch.py
libertem_blobfinder/common/gridmatching.py
libertem_blobfinder/common/patterns.py
libertem_blobfinder/udf/__init__.py
libertem_blobfinder/udf/correlation.py
libertem_blobfinder/udf/integration.py
libertem_blobfinder/udf/refinement.py
libertem_blobfinder/udf/utils.py
libertem_blobfinder-0.6.1.dist-info/METADATA
libertem_blobfinder-0.6.1.dist-info/WHEEL
libertem_blobfinder-0.6.1.dist-info/licenses/LICENSE
libertem_blobfinder-0.6.1.dist-info/RECORD
