Metadata-Version: 2.3
Name: libertem-blobfinder
Version: 0.6.1
Summary: LiberTEM correlation and refinement library
Project-URL: Repository, https://github.com/LiberTEM/LiberTEM-blobfinder
Project-URL: Documentation, https://libertem.github.io/LiberTEM-blobfinder
Author-email: the LiberTEM team <libertem-dev@googlegroups.com>
License-File: LICENSE
Keywords: electron microscopy
Classifier: Development Status :: 4 - Beta
Classifier: Environment :: Console
Classifier: Intended Audience :: Developers
Classifier: Intended Audience :: End Users/Desktop
Classifier: Intended Audience :: Science/Research
Classifier: License :: OSI Approved :: GNU General Public License v3 (GPLv3)
Classifier: Natural Language :: English
Classifier: Operating System :: MacOS :: MacOS X
Classifier: Operating System :: Microsoft :: Windows
Classifier: Operating System :: POSIX :: Linux
Classifier: Programming Language :: Python :: 3.9
Classifier: Programming Language :: Python :: 3.10
Classifier: Programming Language :: Python :: 3.11
Classifier: Programming Language :: Python :: 3.12
Classifier: Topic :: Scientific/Engineering
Classifier: Topic :: Scientific/Engineering :: Physics
Classifier: Topic :: Scientific/Engineering :: Visualization
Requires-Python: >=3.9
Requires-Dist: numba>=0.49
Requires-Dist: numpy
Requires-Dist: scikit-image
Requires-Dist: sparseconverter
Provides-Extra: hdbscan
Requires-Dist: hdbscan; extra == 'hdbscan'
Provides-Extra: udf
Requires-Dist: libertem<1,>=0.12.0; extra == 'udf'
Requires-Dist: matplotlib; extra == 'udf'
